CHANGELOG.rst
LICENSE
MANIFEST.in
README.rst
setup.py
sqlalchemy_filters_2/__init__.py
sqlalchemy_filters_2/exceptions.py
sqlalchemy_filters_2/filters.py
sqlalchemy_filters_2/loads.py
sqlalchemy_filters_2/models.py
sqlalchemy_filters_2/pagination.py
sqlalchemy_filters_2/sorting.py
sqlalchemy_filters_2.egg-info/PKG-INFO
sqlalchemy_filters_2.egg-info/SOURCES.txt
sqlalchemy_filters_2.egg-info/dependency_links.txt
sqlalchemy_filters_2.egg-info/requires.txt
sqlalchemy_filters_2.egg-info/top_level.txt
sqlalchemy_filters_2.egg-info/zip-safe