Metadata-Version: 2.1
Name: sqlalchemy-filters-2
Version: 0.2.0
Summary: A library to filter SQLAlchemy queries.
Home-page: https://github.com/saurabht85/sqlalchemy-filters
Author: Saurabh
Author-email: tewary.saurabh@hotmail.com, drg0072@gmail.com
License: Apache License, Version 2.0
Platform: UNKNOWN
Classifier: Intended Audience :: Developers
Classifier: License :: OSI Approved :: Apache Software License
Classifier: Operating System :: OS Independent
Classifier: Programming Language :: Python
Classifier: Programming Language :: Python :: 3
Classifier: Programming Language :: Python :: 3.5
Classifier: Programming Language :: Python :: 3.6
Classifier: Programming Language :: Python :: 3.7
Classifier: Programming Language :: Python :: 3.8
Classifier: Topic :: Database
Classifier: Topic :: Database :: Front-Ends
Classifier: Topic :: Software Development :: Libraries :: Python Modules
Provides-Extra: postgresql
Provides-Extra: dev
Provides-Extra: python2
Provides-Extra: mysql
